odoo/addons/l10n_es_sigaus_purchase/README.rst
odoo/addons/l10n_es_sigaus_purchase/__init__.py
odoo/addons/l10n_es_sigaus_purchase/__manifest__.py
odoo/addons/l10n_es_sigaus_purchase/hooks.py
odoo/addons/l10n_es_sigaus_purchase/i18n/ca.po
odoo/addons/l10n_es_sigaus_purchase/i18n/es.po
odoo/addons/l10n_es_sigaus_purchase/i18n/l10n_es_sigaus_purchase.pot
odoo/addons/l10n_es_sigaus_purchase/models/__init__.py
odoo/addons/l10n_es_sigaus_purchase/models/account_move.py
odoo/addons/l10n_es_sigaus_purchase/models/purchase_order.py
odoo/addons/l10n_es_sigaus_purchase/models/purchase_order_line.py
odoo/addons/l10n_es_sigaus_purchase/readme/CONFIGURE.rst
odoo/addons/l10n_es_sigaus_purchase/readme/CONTRIBUTORS.rst
odoo/addons/l10n_es_sigaus_purchase/readme/DESCRIPTION.rst
odoo/addons/l10n_es_sigaus_purchase/readme/USAGE.rst
odoo/addons/l10n_es_sigaus_purchase/report/purchase_order_templates.xml
odoo/addons/l10n_es_sigaus_purchase/report/purchase_quotation_templates.xml
odoo/addons/l10n_es_sigaus_purchase/static/description/icon.png
odoo/addons/l10n_es_sigaus_purchase/static/description/icon.svg
odoo/addons/l10n_es_sigaus_purchase/static/description/index.html
odoo/addons/l10n_es_sigaus_purchase/tests/__init__.py
odoo/addons/l10n_es_sigaus_purchase/tests/test_l10n_es_sigaus_purchase.py
odoo/addons/l10n_es_sigaus_purchase/views/purchase_views.xml
odoo_addon_l10n_es_sigaus_purchase-16.0.1.0.3.dist-info/METADATA
odoo_addon_l10n_es_sigaus_purchase-16.0.1.0.3.dist-info/WHEEL
odoo_addon_l10n_es_sigaus_purchase-16.0.1.0.3.dist-info/top_level.txt
odoo_addon_l10n_es_sigaus_purchase-16.0.1.0.3.dist-info/RECORD
